mcp_salesforce_lite/__init__.py
mcp_salesforce_lite/client.py
mcp_salesforce_lite/server.py
mcp_salesforce_lite/tools/__init__.py
mcp_salesforce_lite/tools/crud_tools.py
mcp_salesforce_lite/tools/metadata_tools.py
mcp_salesforce_lite/tools/query_tools.py
mcp_salesforce_lite-0.1.1.dist-info/LICENSE
mcp_salesforce_lite-0.1.1.dist-info/METADATA
mcp_salesforce_lite-0.1.1.dist-info/WHEEL
mcp_salesforce_lite-0.1.1.dist-info/entry_points.txt
mcp_salesforce_lite-0.1.1.dist-info/RECORD
