Metadata-Version: 2.3
Name: mcp-salesforce-lite
Version: 0.1.1
Summary: Simple and lightweight Salesforce MCP server for connecting AI assistants to Salesforce data
License: MIT
Keywords: salesforce,mcp,ai,assistant,crm
Author: luvl
Author-email: linhnd34.jp@gmail.com
Requires-Python: >=3.10
Classifier: Development Status :: 4 - Beta
Classifier: Intended Audience :: Developers
Classifier: License :: OSI Approved :: MIT License
Classifier: Programming Language :: Python :: 3
Classifier: Programming Language :: Python :: 3.10
Classifier: Programming Language :: Python :: 3.11
Classifier: Programming Language :: Python :: 3.12
Classifier: Topic :: Software Development :: Libraries :: Python Modules
Classifier: Topic :: Office/Business
Requires-Dist: mcp (>=1.0.0)
Requires-Dist: python-dotenv (>=1.0.0)
Requires-Dist: simple-salesforce (>=1.12.0)
Project-URL: Homepage, https://github.com/luvl/mcp-salesforce-lite
Project-URL: Issues, https://github.com/luvl/mcp-salesforce-lite/issues
Project-URL: Repository, https://github.com/luvl/mcp-salesforce-lite
